pp_role_mining/SN_Tools.py
pp_role_mining/Utilities.py
pp_role_mining/__init__.py
pp_role_mining/evaluation.py
pp_role_mining/privacyPreserving.py
pp_role_mining-0.0.10.dist-info/LICENSE
pp_role_mining-0.0.10.dist-info/METADATA
pp_role_mining-0.0.10.dist-info/WHEEL
pp_role_mining-0.0.10.dist-info/pbr.json
pp_role_mining-0.0.10.dist-info/top_level.txt
pp_role_mining-0.0.10.dist-info/RECORD
