Metadata-Version: 2.1
Name: pp-role-mining
Version: 0.0.10
Summary: Privacy Aware Role Mining in Process mining
Home-page: https://github.com/m4jidRafiei/privacyAware-roleMining
Author: Majid Rafiei
Author-email: majid.rafiei@pads.rwth-aachen.de
License: GPL 3.0
Project-URL: Source, https://github.com/m4jidRafiei/privacyAware-roleMining
Platform: UNKNOWN
Requires-Dist: pm4py (==1.2.10)
Requires-Dist: distributed (==1.21.8)
Requires-Dist: pycrypto (==2.6.1)
Requires-Dist: p-privacy-metadata (==0.0.4)
Requires-Dist: networkx (==2.3)
Requires-Dist: matplotlib (==2.2.2)
Requires-Dist: numpy (==1.18.1)
Requires-Dist: pyvis (==0.1.4.1)
